data_profile/__init__.py
data_profile/exception/__init__.py
data_profile/exception/exception.py
data_profile/logging/__init__.py
data_profile/logging/logger.py
ml_data_profile-0.1.4.6.dist-info/METADATA
ml_data_profile-0.1.4.6.dist-info/WHEEL
ml_data_profile-0.1.4.6.dist-info/top_level.txt
ml_data_profile-0.1.4.6.dist-info/RECORD
