Metadata-Version: 2.4
Name: ML-data-profile
Version: 0.1.4.6
Summary: Data profiling utilities
Project-URL: Homepage, https://github.com/Jagadeesha89/ML-data-profile
Project-URL: Bug Tracker, https://github.com/Jagadeesha89/ML-data-profile/issues
Requires-Python: >=3.11
Requires-Dist: scipy>=1.17.0
Requires-Dist: seaborn>=0.13.2
